mxdc/__init__.py
mxdc/consoleapp.py
mxdc/hutchapp.py
mxdc/imageapp.py
mxdc/mxdcapp.py
mxdc/version.py
mxdc/beamlines/__init__.py
mxdc/beamlines/mx.py
mxdc/com/__init__.py
mxdc/com/ca.py
mxdc/conf/__init__.py
mxdc/conf/settings.py
mxdc/controllers/__init__.py
mxdc/controllers/analysis.py
mxdc/controllers/automounter.py
mxdc/controllers/browser.py
mxdc/controllers/chat.py
mxdc/controllers/common.py
mxdc/controllers/cryo.py
mxdc/controllers/datasets.py
mxdc/controllers/diagnostics.py
mxdc/controllers/humidity.py
mxdc/controllers/microscope.py
mxdc/controllers/ptzvideo.py
mxdc/controllers/rastering.py
mxdc/controllers/samples.py
mxdc/controllers/samplestore.py
mxdc/controllers/scanplot.py
mxdc/controllers/scans.py
mxdc/controllers/settings.py
mxdc/controllers/setup.py
mxdc/controllers/status.py
mxdc/devices/__init__.py
mxdc/devices/boss.py
mxdc/devices/center.py
mxdc/devices/counter.py
mxdc/devices/cryojet.py
mxdc/devices/detector.py
mxdc/devices/diagnostics.py
mxdc/devices/goniometer.py
mxdc/devices/humidity.py
mxdc/devices/interfaces.py
mxdc/devices/manager.py
mxdc/devices/mca.py
mxdc/devices/misc.py
mxdc/devices/motor.py
mxdc/devices/shutter.py
mxdc/devices/stages.py
mxdc/devices/synchrotron.py
mxdc/devices/video.py
mxdc/devices/automounter/__init__.py
mxdc/devices/automounter/cats.py
mxdc/devices/automounter/isara.py
mxdc/devices/automounter/sam.py
mxdc/devices/automounter/sim.py
mxdc/engines/__init__.py
mxdc/engines/analysis.py
mxdc/engines/auto.py
mxdc/engines/automation.py
mxdc/engines/centering.py
mxdc/engines/chooch.py
mxdc/engines/diffraction.py
mxdc/engines/humidity.py
mxdc/engines/interfaces.py
mxdc/engines/rastering.py
mxdc/engines/scanning.py
mxdc/engines/scripting.py
mxdc/engines/scripts.py
mxdc/engines/spectroscopy.py
mxdc/services/__init__.py
mxdc/services/archiver.py
mxdc/services/clients.py
mxdc/services/imagesync.py
mxdc/services/interfaces.py
mxdc/services/server.py
mxdc/share/dark.mplstyle
mxdc/share/gschemas.compiled
mxdc/share/imgsync.tac
mxdc-2020.8.24.dist-info/LICENSE
mxdc-2020.8.24.dist-info/METADATA
mxdc-2020.8.24.dist-info/WHEEL
mxdc-2020.8.24.dist-info/top_level.txt
mxdc-2020.8.24.dist-info/RECORD
