Metadata-Version: 2.1
Name: mxdc
Version: 2020.8.24
Summary: Mx Data Collector
Home-page: https://github.com/michel4j/mxdc
Author: Michel Fodje
Author-email: michel4j@gmail.com
License: MIT
Keywords: beamline data-acquisition crystallography MX
Platform: UNKNOWN
Classifier: Intended Audience :: Developers
Classifier: Programming Language :: Python :: 3
Classifier: License :: OSI Approved :: MIT License
Classifier: Operating System :: OS Independent
Requires-Dist: numpy
Requires-Dist: lz4
Requires-Dist: pyzmq
Requires-Dist: cryptography
Requires-Dist: gepics
Requires-Dist: h5py
Requires-Dist: hdf5plugin
Requires-Dist: matplotlib
Requires-Dist: msgpack
Requires-Dist: opencv-python
Requires-Dist: pillow
Requires-Dist: PyGObject
Requires-Dist: pyyaml
Requires-Dist: redis
Requires-Dist: requests
Requires-Dist: scipy
Requires-Dist: twisted
Requires-Dist: zeroconf
Requires-Dist: python-magic
Requires-Dist: pytz
Requires-Dist: ipython
Requires-Dist: mxio
Requires-Dist: humanize
Requires-Dist: lorem
Requires-Dist: backports-datetime-fromisoformat
Requires-Dist: importlib-metadata (~=1.0) ; python_version < "3.8"
